MANIFEST.in
README.rst
requirements.txt
setup.cfg
setup.py
todo.rst
docs/Makefile
docs/source/api-reference.rst
docs/source/conf.py
docs/source/index.rst
docs/source/introduction.rst
docs/source/tutorial.rst
plural/__init__.py
plural/client.py
plural/codec.py
plural/console.py
plural/exceptions.py
plural/query.py
plural/repl.py
plural/server.py
plural/store.py
plural/util.py
plural/version.py
plural.egg-info/PKG-INFO
plural.egg-info/SOURCES.txt
plural.egg-info/dependency_links.txt
plural.egg-info/entry_points.txt
plural.egg-info/not-zip-safe
plural.egg-info/requires.txt
plural.egg-info/top_level.txt
plural/models/__init__.py
plural/models/edges.py
plural/models/element.py
plural/models/vertices.py
plural/models/meta/__init__.py
plural/models/meta/edges.py
plural/models/meta/vertices.py