Metadata-Version: 1.0
Name: plural
Version: 0.2.0
Summary: UNKNOWN
Home-page: https://github.com/gabrielfalcao/plural
Author: Gabriel Falcao
Author-email: gabriel@nacaolivre.org
License: UNKNOWN
Platform: UNKNOWN
